{
  "$schema": "http://json-schema.org/draft-07/schema#",
  "$id": "https://protocol.isimip.org/schema/schema/ISIMIP3a/OutputData/agriculture.yaml",
  "commit": "f02046b0f8168faa0b6e414db37fb640626d7858",
  "type": "object",
  "required": [
    "specifiers"
  ],
  "properties": {
    "specifiers": {
      "required": [
        "model",
        "climate_forcing",
        "climate_scenario",
        "soc_scenario",
        "sens_scenario",
        "variable",
        "crop",
        "irrigation",
        "region",
        "time_step"
      ],
      "properties": {
        "model": {
          "type": "string"
        },
        "climate_forcing": {
          "type": "string",
          "enum": [
            "20crv3",
            "gswp3-w5e5",
            "20crv3-era5",
            "20crv3-w5e5",
            "chelsa-w5e5"
          ]
        },
        "detrending": {
          "type": "string",
          "enum": [
            "observed",
            "detrended"
          ]
        },
        "climate_scenario": {
          "type": "string",
          "enum": [
            "counterclim",
            "obsclim"
          ]
        },
        "soc_scenario": {
          "type": "string",
          "enum": [
            "2015soc",
            "histsoc"
          ]
        },
        "sens_scenario": {
          "type": "string",
          "enum": [
            "default",
            "1901co2",
            "300arcsec",
            "1800arcsec",
            "90arcsec",
            "30arcsec"
          ]
        },
        "variable": {
          "type": "string",
          "enum": [
            "nincum",
            "nupcum",
            "biom",
            "nleachcum",
            "pirnreqcum",
            "anthday",
            "matyday",
            "harvyear",
            "initrcum",
            "evapcum",
            "nlosscum",
            "soilmoist",
            "yield",
            "plantday",
            "plantyear"
          ]
        },
        "crop": {
          "type": "string",
          "enum": [
            "euc",
            "sor",
            "wwh",
            "pop",
            "whe",
            "swh",
            "bea",
            "pot",
            "cas",
            "nut",
            "sun",
            "mis",
            "cot",
            "mai",
            "mgr",
            "bar",
            "rap",
            "sgc",
            "ri2",
            "ric",
            "mil",
            "sgb",
            "ri1",
            "soy",
            "rye",
            "pea"
          ]
        },
        "irrigation": {
          "type": "string",
          "enum": [
            "firr",
            "noirr"
          ]
        },
        "region": {
          "type": "string",
          "enum": [
            "europe",
            "along-track",
            "global"
          ]
        },
        "time_step": {
          "type": "string",
          "enum": [
            "hourly",
            "monthly",
            "fixed",
            "daily",
            "monthly-gs",
            "3hr",
            "annual",
            "annual-gs"
          ]
        },
        "start_year": {
          "type": "number"
        },
        "end_year": {
          "type": "number"
        }
      }
    }
  }
}