{
  "$schema": "http://json-schema.org/draft-07/schema#",
  "$id": "https://protocol.isimip.org/schema/schema/ISIMIP3a/OutputData/forestry.json",
  "commit": "a63efdf56237cb1b3ed061fc003266de96d13836",
  "type": "object",
  "required": [
    "specifiers"
  ],
  "properties": {
    "specifiers": {
      "required": [
        "model",
        "climate_forcing",
        "climate_scenario",
        "soc_scenario",
        "sens_scenario",
        "variable",
        "forest_stand",
        "time_step"
      ],
      "properties": {
        "model": {
          "type": "string"
        },
        "climate_forcing": {
          "type": "string",
          "enum": [
            "gswp3-w5e5",
            "20crv3-era5",
            "20crv3",
            "chelsa-w5e5v1.0",
            "20crv3-w5e5"
          ]
        },
        "detrending": {
          "type": "string",
          "enum": [
            "observed",
            "detrended"
          ]
        },
        "climate_scenario": {
          "type": "string",
          "enum": [
            "obsclim"
          ]
        },
        "soc_scenario": {
          "type": "string",
          "enum": [
            "2015soc",
            "histsoc"
          ]
        },
        "sens_scenario": {
          "type": "string",
          "enum": [
            "90arcsec",
            "1901co2",
            "1800arcsec",
            "30arcsec",
            "300arcsec",
            "default"
          ]
        },
        "variable": {
          "type": "string",
          "enum": [
            "clitterag",
            "ccwd",
            "croot",
            "dbh",
            "evap",
            "cvegbg",
            "intercep",
            "hei",
            "cwood",
            "cleaf",
            "esoil",
            "rr",
            "ra",
            "rh",
            "nee",
            "dbhdomhei",
            "density",
            "soil",
            "domhei",
            "lai",
            "age",
            "clitterbg",
            "cvegag",
            "mortstemno",
            "npp",
            "soilmoist",
            "nsoil",
            "gpp",
            "harv",
            "species",
            "nlitterag",
            "ba",
            "tsl",
            "csoil",
            "csoillayer",
            "fapar",
            "cveg",
            "vol",
            "cproduct",
            "stemno",
            "trans",
            "nlitterbg",
            "dist",
            "mort",
            "harvstemno",
            "mai"
          ]
        },
        "species": {
          "type": "string",
          "enum": [
            "hawo",
            "bepe",
            "c3gr",
            "piab",
            "qupe",
            "acpl",
            "rops",
            "pisy",
            "bepu",
            "ins",
            "quro",
            "wi",
            "fasy",
            "lade",
            "pipi",
            "soau",
            "poni",
            "fi",
            "frex",
            "eugl"
          ]
        },
        "forest_stand": {
          "type": "string",
          "enum": [
            "collelongo",
            "peitz",
            "solling-beech",
            "hyytiala",
            "le-bray",
            "solling-spruce",
            "kroof",
            "soro",
            "bily-kriz"
          ]
        },
        "time_step": {
          "type": "string",
          "enum": [
            "fixed",
            "daily",
            "3hr",
            "monthly",
            "annual"
          ]
        },
        "start_year": {
          "type": "number"
        },
        "end_year": {
          "type": "number"
        }
      }
    }
  }
}