{
  "$schema": "http://json-schema.org/draft-07/schema#",
  "$id": "https://protocol.isimip.org/schema/schema/ISIMIP3a/OutputData/marine-fishery_regional.yaml",
  "commit": "c55a757a74e753805000055568a2b0cf3fbf8638",
  "type": "object",
  "required": [
    "specifiers"
  ],
  "properties": {
    "specifiers": {
      "required": [
        "model",
        "climate_forcing",
        "climate_scenario",
        "soc_scenario",
        "sens_scenario",
        "variable",
        "region",
        "time_step"
      ],
      "properties": {
        "model": {
          "type": "string"
        },
        "climate_forcing": {
          "type": "string",
          "enum": [
            "gfdl-mom6-cobalt2"
          ]
        },
        "detrending": {
          "type": "string",
          "enum": [
            "detrended",
            "observed"
          ]
        },
        "climate_scenario": {
          "type": "string",
          "enum": [
            "obsclim"
          ]
        },
        "soc_scenario": {
          "type": "string",
          "enum": [
            "histsoc",
            "nat"
          ]
        },
        "sens_scenario": {
          "type": "string",
          "enum": [
            "1955-riverine-input+60arcmin",
            "default",
            "60arcmin",
            "1955-riverine-input"
          ]
        },
        "variable": {
          "type": "string",
          "enum": [
            "cd30to90cm",
            "cd30cm",
            "tcblog10",
            "tclog10",
            "tcb",
            "cp30cm",
            "bp90cm",
            "bp30to90cm",
            "bd30to90cm",
            "cp90cm",
            "tdb",
            "bp30cm",
            "tpc",
            "tpb",
            "tc",
            "bd90cm",
            "tdc",
            "cd90cm",
            "bd30cm",
            "cp30to90cm"
          ]
        },
        "region": {
          "type": "string",
          "enum": [
            "global",
            "along-track",
            "europe"
          ]
        },
        "time_step": {
          "type": "string",
          "enum": [
            "monthly",
            "daily",
            "annual",
            "3hr",
            "hourly",
            "fixed"
          ]
        },
        "start_year": {
          "type": "number"
        },
        "end_year": {
          "type": "number"
        }
      }
    }
  }
}