{
  "$schema": "http://json-schema.org/draft-07/schema#",
  "$id": "https://protocol.isimip.org/schema/schema/ISIMIP3a/OutputData/peat.json",
  "commit": "cbe348a95ef3f8fad12d7886e6ec16d2def5a531",
  "type": "object",
  "required": [
    "specifiers"
  ],
  "properties": {
    "specifiers": {
      "required": [
        "model",
        "climate_forcing",
        "climate_scenario",
        "soc_scenario",
        "sens_scenario",
        "variable",
        "region",
        "time_step"
      ],
      "properties": {
        "model": {
          "type": "string"
        },
        "climate_forcing": {
          "type": "string",
          "enum": [
            "gswp3-w5e5",
            "20crv3",
            "20crv3-w5e5",
            "20crv3-era5"
          ]
        },
        "detrending": {
          "type": "string",
          "enum": [
            "observed",
            "detrended"
          ]
        },
        "climate_scenario": {
          "type": "string",
          "enum": [
            "obsclim",
            "counterclim"
          ]
        },
        "soc_scenario": {
          "type": "string",
          "enum": [
            "histsoc",
            "1901soc",
            "2015soc",
            "nat"
          ]
        },
        "sens_scenario": {
          "type": "string",
          "enum": [
            "1901co2",
            "default",
            "nofire"
          ]
        },
        "variable": {
          "type": "string",
          "enum": [
            "fndep",
            "snd",
            "fbnf",
            "peatdepth",
            "cwood",
            "nvegag",
            "fgrazing",
            "nloss",
            "fnproduct",
            "fcropharvest",
            "fngas",
            "wetlandch4",
            "fnlittersoil",
            "npp",
            "flittersoil",
            "fnanthdisturb",
            "hydcon",
            "fvegsoil",
            "fn2o",
            "fnnetmin",
            "landalbedo",
            "fnvegsoil",
            "csoillayer",
            "lai",
            "trans",
            "fapar",
            "rhlayer",
            "swe",
            "rlitter",
            "sm15",
            "tsl",
            "fnfert",
            "rsoillayer",
            "nveg",
            "fnh3",
            "wt",
            "potevap",
            "intercep",
            "drainagedensity",
            "nbp",
            "ffire",
            "drainagedepth",
            "cleaf",
            "sm5",
            "doc",
            "nmineralno3",
            "dis",
            "nlitterbg",
            "gpp",
            "cvegag",
            "qs",
            "thawdepth",
            "fnveglitter",
            "nlitterag",
            "burntarea",
            "socage",
            "ch4",
            "tws",
            "cproduct",
            "cvegbg",
            "fluc",
            "peattypefrac",
            "ra",
            "nproduct",
            "sm15000",
            "sm330",
            "rh",
            "clitterbg",
            "nmineral",
            "verticalcflux",
            "nmineralnh4",
            "csoil",
            "soil",
            "qtot",
            "wetlandfrac",
            "flitter",
            "fngasfire",
            "smsat",
            "pft",
            "wf",
            "cveg",
            "fnleach",
            "flittersoillayer",
            "ccwd",
            "clitterag",
            "sm50",
            "soilmoistfroz",
            "qsb",
            "nvegbg",
            "fvegsoillayer",
            "evap",
            "esoil",
            "croot",
            "nsoil"
          ]
        },
        "crop": {
          "type": "string",
          "enum": [
            "cot",
            "euc",
            "ri1",
            "mai",
            "ric",
            "soy",
            "sgb",
            "mgr",
            "pot",
            "mis",
            "rap",
            "swh",
            "mil",
            "sgc",
            "nut",
            "ri2",
            "pea",
            "rye",
            "cas",
            "sor",
            "whe",
            "wwh",
            "bea",
            "pop",
            "sun",
            "bar"
          ]
        },
        "irrigation": {
          "type": "string",
          "enum": [
            "noirr"
          ]
        },
        "pft": {
          "type": "string"
        },
        "pool": {
          "type": "string",
          "enum": [
            "passive",
            "slow",
            "fast"
          ]
        },
        "pt": {
          "type": "string"
        },
        "region": {
          "type": "string",
          "enum": [
            "global"
          ]
        },
        "time_step": {
          "type": "string",
          "enum": [
            "monthly",
            "annual",
            "daily",
            "3hr",
            "fixed"
          ]
        },
        "start_year": {
          "type": "number"
        },
        "end_year": {
          "type": "number"
        }
      }
    }
  }
}