{
  "$schema": "http://json-schema.org/draft-07/schema#",
  "$id": "https://protocol.isimip.org/schema/schema/ISIMIP3a/OutputData/permafrost.json",
  "commit": "31822f2437873425fbd730aa0dea29ad453b8919",
  "type": "object",
  "required": [
    "specifiers"
  ],
  "properties": {
    "specifiers": {
      "required": [
        "model",
        "climate_forcing",
        "climate_scenario",
        "soc_scenario",
        "sens_scenario",
        "variable",
        "region",
        "time_step"
      ],
      "properties": {
        "model": {
          "type": "string"
        },
        "climate_forcing": {
          "type": "string",
          "enum": [
            "gswp3",
            "gswp3-w5e5"
          ]
        },
        "detrending": {
          "type": "string",
          "enum": [
            "detrended",
            "observed"
          ]
        },
        "climate_scenario": {
          "type": "string",
          "enum": [
            "spinclim",
            "counterclim",
            "obsclim"
          ]
        },
        "soc_scenario": {
          "type": "string",
          "enum": [
            "2015soc",
            "histsoc",
            "nat"
          ]
        },
        "sens_scenario": {
          "type": "string",
          "enum": [
            "default",
            "1901co2"
          ]
        },
        "variable": {
          "type": "string",
          "enum": [
            "tsl",
            "ra",
            "pft",
            "clitterbg",
            "swe",
            "npp",
            "ffire",
            "fluc",
            "rh",
            "burntarea",
            "thawdepth",
            "qs",
            "cwood",
            "croot",
            "landalbedo",
            "snd",
            "qtot",
            "fapar",
            "csoil",
            "cvegbg",
            "nbp",
            "lai",
            "flitter",
            "fcropharvest",
            "fvegsoil",
            "fgrazing",
            "cleaf",
            "soilmoistfroz",
            "clitterag",
            "cveg",
            "gpp",
            "cvegag",
            "ccwd",
            "soilmoist",
            "flittersoil"
          ]
        },
        "crop": {
          "type": "string",
          "enum": [
            "cot",
            "mgr",
            "bar",
            "mai",
            "rap",
            "ben",
            "sun",
            "pea",
            "whe",
            "mil",
            "ric",
            "pot",
            "cas",
            "pop",
            "nut",
            "mis",
            "sgb",
            "sor",
            "sug",
            "euc",
            "soy",
            "rye"
          ]
        },
        "irrigation": {
          "type": "string",
          "enum": [
            "noirr"
          ]
        },
        "pft": {
          "type": "string"
        },
        "region": {
          "type": "string",
          "enum": [
            "global"
          ]
        },
        "time_step": {
          "type": "string",
          "enum": [
            "monthly",
            "fixed",
            "3hr",
            "daily",
            "annual"
          ]
        },
        "start_year": {
          "type": "number"
        },
        "end_year": {
          "type": "number"
        }
      }
    }
  }
}