{
  "$schema": "http://json-schema.org/draft-07/schema#",
  "$id": "https://protocol.isimip.org/schema/schema/ISIMIP3a/InputData/climate/atmosphere_composition.yaml",
  "commit": "15a57848aae0db4d69ca1bd9106f6ccf0c4aad62",
  "type": "object",
  "required": [
    "specifiers"
  ],
  "properties": {
    "specifiers": {
      "type": "object",
      "required": [
        "climate_variable",
        "climate_scenario",
        "time_step"
      ],
      "properties": {
        "climate_variable": {
          "type": "string",
          "enum": [
            "96knarea",
            "34knassets",
            "64knassets",
            "rsntds",
            "waterlevel",
            "intppmisc",
            "so",
            "basin",
            "thkcello",
            "co2",
            "maxrain",
            "windlifetimemax",
            "pres",
            "tasmin",
            "v850",
            "uo",
            "windspatialmax",
            "tas",
            "prsn",
            "48knassets",
            "expc",
            "mlotst",
            "wind",
            "intpp",
            "48knpop",
            "tasmax",
            "time",
            "rlds",
            "intppdiaz",
            "96knpop",
            "phydiat",
            "u850",
            "siconc",
            "orog",
            "48knarea",
            "huss",
            "ph",
            "tob",
            "tos",
            "pr",
            "lon",
            "lat",
            "64knarea",
            "34knpop",
            "mask",
            "geocentricwaterlevel",
            "vo",
            "ch4",
            "zmeso",
            "ps",
            "phydiaz",
            "phypico",
            "intppdiat",
            "thetao",
            "rmw",
            "34knarea",
            "rain",
            "lightning",
            "96knassets",
            "intpppico",
            "chl",
            "o2",
            "64knpop",
            "hurs",
            "roci",
            "sfcwind",
            "intpoc",
            "zmicro",
            "t600",
            "phyc",
            "zooc",
            "penv",
            "rsds"
          ]
        },
        "climate_scenario": {
          "type": "string",
          "enum": [
            "obsclim",
            "spinclim",
            "ctrlclim",
            "transclim",
            "counterclim"
          ]
        },
        "time_step": {
          "type": "string",
          "enum": [
            "annual",
            "annual-gs",
            "monthly",
            "monthly-gs",
            "fixed",
            "daily",
            "6hr",
            "2hr",
            "3hr",
            "hourly"
          ]
        },
        "start_year": {
          "type": "number"
        },
        "end_year": {
          "type": "number"
        }
      }
    }
  }
}