{
  "$schema": "http://json-schema.org/draft-07/schema#",
  "$id": "https://protocol.isimip.org/schema/schema/ISIMIP3a/InputData/climate/sealevel.json",
  "commit": "5d1bd16ead8ad211b2c0bad7101414da07bd4353",
  "type": "object",
  "required": [
    "specifiers"
  ],
  "properties": {
    "specifiers": {
      "type": "object",
      "required": [
        "climate_dataset",
        "climate_scenario",
        "climate_variable",
        "region",
        "time_step"
      ],
      "properties": {
        "climate_dataset": {
          "type": "string",
          "enum": [
            "hcc"
          ]
        },
        "climate_scenario": {
          "type": "string",
          "enum": [
            "obsclim",
            "ctrlclim",
            "transclim",
            "counterclim",
            "spinclim"
          ]
        },
        "climate_variable": {
          "type": "string",
          "enum": [
            "phydiaz",
            "intppdiaz",
            "prsn",
            "tasmax",
            "ch4",
            "so",
            "lightning",
            "rlds",
            "tasmin",
            "mask",
            "zooc",
            "phypico",
            "mlotst",
            "geocentricwaterlevel",
            "intpp",
            "tob",
            "zmicro",
            "huss",
            "siconc",
            "zmeso",
            "intpppico",
            "uo",
            "phyc",
            "intppdiat",
            "intpoc",
            "ps",
            "rsntds",
            "o2",
            "thkcello",
            "intppmisc",
            "co2",
            "vo",
            "tas",
            "chl",
            "pr",
            "phydiat",
            "rsds",
            "expc",
            "tos",
            "orog",
            "hurs",
            "ph",
            "waterlevel",
            "thetao",
            "sfcwind"
          ]
        },
        "region": {
          "type": "string",
          "enum": [
            "global"
          ]
        },
        "time_step": {
          "type": "string",
          "enum": [
            "daily",
            "hourly",
            "monthly",
            "annual",
            "annual-gs",
            "fixed",
            "monthly-gs"
          ]
        },
        "start_year": {
          "type": "number"
        },
        "end_year": {
          "type": "number"
        }
      }
    }
  }
}