{
  "$schema": "http://json-schema.org/draft-07/schema#",
  "$id": "https://protocol.isimip.org/schema/schema/ISIMIP3b/SecondaryOutputData/forestry.json",
  "commit": "886f82168ad951c60814cf9b69308701d0565217",
  "type": "object",
  "required": [
    "specifiers"
  ],
  "properties": {
    "specifiers": {
      "required": [
        "model",
        "climate_forcing",
        "bias_adjustment",
        "climate_scenario",
        "soc_scenario",
        "sens_scenario",
        "variable",
        "forest_stand",
        "time_step"
      ],
      "properties": {
        "model": {
          "type": "string"
        },
        "climate_forcing": {
          "type": "string",
          "enum": [
            "miroc6",
            "ipsl-cm6a-lr",
            "cnrm-esm2-1",
            "mri-esm2-0",
            "ec-earth3",
            "cnrm-cm6-1",
            "gfdl-esm4",
            "canesm5",
            "mpi-esm1-2-hr",
            "ukesm1-0-ll"
          ]
        },
        "bias_adjustment": {
          "type": "string",
          "enum": [
            "localbc",
            "w5e5",
            "nobasd"
          ]
        },
        "climate_scenario": {
          "type": "string",
          "enum": [
            "historical",
            "picontrol",
            "ssp126",
            "ssp245",
            "ssp534-over",
            "ssp585",
            "ssp370",
            "ssp119",
            "hist-nat",
            "ssp460"
          ]
        },
        "soc_scenario": {
          "type": "string",
          "enum": [
            "ssp3soc",
            "ssp4soc",
            "ssp370soc",
            "ssp2soc",
            "ssp5soc",
            "2015soc",
            "ssp126soc",
            "histsoc",
            "2015soc-from-histsoc",
            "ssp585soc",
            "ssp1soc"
          ]
        },
        "sens_scenario": {
          "type": "string",
          "enum": [
            "default",
            "2015co2"
          ]
        },
        "variable": {
          "type": "string",
          "enum": [
            "cvegag",
            "stemno",
            "soil",
            "vol",
            "soilmoist",
            "nee",
            "age",
            "mort",
            "domhei",
            "dbh",
            "tsl",
            "cleaf",
            "harv",
            "rh",
            "lai",
            "cproduct",
            "ccwd",
            "trans",
            "gpp",
            "hei",
            "harvstemno",
            "nlitterag",
            "npp",
            "evap",
            "dist",
            "csoil",
            "intercep",
            "csoillayer",
            "clitterbg",
            "mai",
            "cwood",
            "croot",
            "ra",
            "esoil",
            "dbhdomhei",
            "nsoil",
            "density",
            "ba",
            "clitterag",
            "fapar",
            "mortstemno",
            "cvegbg",
            "species",
            "nlitterbg",
            "cveg",
            "rr"
          ]
        },
        "species": {
          "type": "string",
          "enum": [
            "quro",
            "fasy",
            "acpl",
            "pipi",
            "wi",
            "lade",
            "hawo",
            "soau",
            "c3gr",
            "ins",
            "qupe",
            "piab",
            "fi",
            "eugl",
            "poni",
            "rops",
            "frex",
            "pisy",
            "bepu",
            "bepe"
          ]
        },
        "forest_stand": {
          "type": "string",
          "enum": [
            "soro",
            "le-bray",
            "bily-kriz",
            "hyytiala",
            "solling-beech",
            "collelongo",
            "solling-spruce",
            "peitz",
            "kroof"
          ]
        },
        "time_step": {
          "type": "string",
          "enum": [
            "3hr",
            "fixed",
            "daily",
            "annual",
            "monthly"
          ]
        },
        "start_year": {
          "type": "number"
        },
        "end_year": {
          "type": "number"
        }
      }
    }
  }
}