{
  "$schema": "http://json-schema.org/draft-07/schema#",
  "$id": "https://protocol.isimip.org/schema/schema/ISIMIP3b/SecondaryOutputData/water_global.json",
  "commit": "886f82168ad951c60814cf9b69308701d0565217",
  "type": "object",
  "required": [
    "specifiers"
  ],
  "properties": {
    "specifiers": {
      "required": [
        "model",
        "climate_forcing",
        "bias_adjustment",
        "climate_scenario",
        "soc_scenario",
        "sens_scenario",
        "variable",
        "region",
        "time_step"
      ],
      "properties": {
        "model": {
          "type": "string"
        },
        "climate_forcing": {
          "type": "string",
          "enum": [
            "miroc6",
            "ipsl-cm6a-lr",
            "cnrm-esm2-1",
            "mri-esm2-0",
            "ec-earth3",
            "cnrm-cm6-1",
            "gfdl-esm4",
            "canesm5",
            "mpi-esm1-2-hr",
            "ukesm1-0-ll"
          ]
        },
        "bias_adjustment": {
          "type": "string",
          "enum": [
            "w5e5",
            "nobasd"
          ]
        },
        "climate_scenario": {
          "type": "string",
          "enum": [
            "historical",
            "picontrol",
            "ssp126",
            "ssp245",
            "ssp534-over",
            "ssp585",
            "ssp370",
            "ssp119",
            "hist-nat",
            "ssp460"
          ]
        },
        "soc_scenario": {
          "type": "string",
          "enum": [
            "ssp3soc",
            "ssp4soc",
            "ssp370soc",
            "1850soc",
            "ssp2soc",
            "ssp5soc",
            "2015soc",
            "ssp126soc",
            "histsoc",
            "2015soc-from-histsoc",
            "ssp585soc",
            "ssp1soc"
          ]
        },
        "sens_scenario": {
          "type": "string",
          "enum": [
            "default",
            "2015co2"
          ]
        },
        "variable": {
          "type": "string",
          "enum": [
            "plantday",
            "pmanww",
            "plivusegw",
            "nleachcum",
            "qtot",
            "pirrww",
            "ptotusegw",
            "rootmoist",
            "airrww",
            "adomwwgw",
            "riverstor",
            "pdomww",
            "nlosscum",
            "evap",
            "pdomwwgw",
            "nupcum",
            "soilmoistfroz",
            "qrf",
            "amanww",
            "pmanwwgw",
            "airrusegw",
            "yield",
            "pelecwwgw",
            "aindwwgw",
            "ptotwwgw",
            "glacierstor",
            "pirrusegreen",
            "ptotww",
            "amanwwgw",
            "soilmoist",
            "pelecuse",
            "airruse",
            "plantyear",
            "alivwwgw",
            "pindusegw",
            "cellarea",
            "pirrusegw",
            "pelecww",
            "swe",
            "tws",
            "adomww",
            "nincum",
            "aindusegw",
            "aelecusegw",
            "alivusegw",
            "adomusegw",
            "pirruse",
            "atotww",
            "evapcum",
            "pirrwwgw",
            "atotusegw",
            "harvyear",
            "aindww",
            "lakestor",
            "soil",
            "amanusegw",
            "tsl",
            "adomuse",
            "pdomusegw",
            "pindwwgw",
            "aelecwwgw",
            "anthday",
            "aliveuse",
            "snd",
            "thawdepth",
            "aliveww",
            "airrwwgw",
            "groundwstor",
            "plivwwgw",
            "wetlandstor",
            "arainfusegreen",
            "aelecuse",
            "pirnreqcum",
            "amanuse",
            "atotuse",
            "triver",
            "reservoirstor",
            "contfrac",
            "pliveuse",
            "initrcum",
            "atotwwgw",
            "qsb",
            "ainduse",
            "qr",
            "potevap",
            "qrd",
            "pelecusegw",
            "pindww",
            "dis",
            "lai",
            "pinduse",
            "ptotuse",
            "biom",
            "pmanusegw",
            "pdomuse",
            "aelecww",
            "pliveww",
            "pmanuse",
            "qg",
            "matyday",
            "qs",
            "canopystor",
            "airrusegreen"
          ]
        },
        "crop": {
          "type": "string",
          "enum": [
            "wwh",
            "pea",
            "sgc",
            "rap",
            "mgr",
            "bea",
            "rye",
            "whe",
            "mis",
            "euc",
            "pot",
            "cas",
            "sor",
            "nut",
            "ri2",
            "swh",
            "ric",
            "mil",
            "pop",
            "mai",
            "ri1",
            "bar",
            "soy",
            "sgb",
            "sun",
            "cot"
          ]
        },
        "irrigation": {
          "type": "string",
          "enum": [
            "cirr",
            "noirr"
          ]
        },
        "pft": {
          "type": "string"
        },
        "region": {
          "type": "string",
          "enum": [
            "global"
          ]
        },
        "time_step": {
          "type": "string",
          "enum": [
            "3hr",
            "fixed",
            "daily",
            "annual",
            "monthly"
          ]
        },
        "start_year": {
          "type": "number"
        },
        "end_year": {
          "type": "number"
        }
      }
    }
  }
}