{
  "$schema": "http://json-schema.org/draft-07/schema#",
  "$id": "https://protocol.isimip.org/schema/schema/ISIMIP3a/SecondaryInputData/climate/atmosphere.json",
  "commit": "69a174c0c25c0555be8e04cf39cfc305539a2900",
  "type": "object",
  "required": [
    "specifiers"
  ],
  "properties": {
    "specifiers": {
      "type": "object",
      "required": [
        "climate_forcing",
        "climate_scenario",
        "climate_variable",
        "region",
        "time_step"
      ],
      "properties": {
        "climate_forcing": {
          "type": "string",
          "enum": [
            "w5e5v1.0",
            "cesm2",
            "chelsa-w5e5v1.0",
            "w5e5v2.0",
            "gswp3-w5e5"
          ]
        },
        "climate_scenario": {
          "type": "string",
          "enum": [
            "obsclim",
            "counterclim",
            "ctrlclim"
          ]
        },
        "climate_variable": {
          "type": "string",
          "enum": [
            "intpppico",
            "intppdiaz",
            "co2",
            "tob",
            "hur",
            "intpp",
            "chl",
            "intppmisc",
            "hus",
            "orog",
            "ph",
            "mlotst",
            "zmicro",
            "zmeso",
            "tasmin",
            "phyc",
            "ua",
            "phydiaz",
            "expc",
            "lightning",
            "hurs",
            "ts",
            "huss",
            "rsds",
            "rsntds",
            "siconc",
            "prw",
            "pr",
            "intppdiat",
            "intpoc",
            "o2",
            "ch4",
            "psl",
            "tos",
            "prsn",
            "va",
            "mask",
            "tas",
            "tasmax",
            "thetao",
            "rlds",
            "sfcwind",
            "phypico",
            "thkcello",
            "vo",
            "ta",
            "phydiat",
            "so",
            "uo",
            "zooc",
            "ps"
          ]
        },
        "resolution": {
          "type": "string",
          "enum": [
            "15arcmin",
            "120arcmin",
            "30arcmin",
            "60arcmin"
          ]
        },
        "region": {
          "type": "string",
          "enum": [
            "global"
          ]
        },
        "time_step": {
          "type": "string",
          "enum": [
            "monthly",
            "annual",
            "daily",
            "fixed"
          ]
        },
        "start_year": {
          "type": "number"
        },
        "end_year": {
          "type": "number"
        }
      }
    }
  }
}