{
  "$schema": "http://json-schema.org/draft-07/schema#",
  "$id": "https://protocol.isimip.org/schema/schema/ISIMIP3b/InputData/climate/ocean.json",
  "commit": "5d1bd604b6044b03303d3d09a6ef8ad277ef4144",
  "type": "object",
  "required": [
    "specifiers"
  ],
  "properties": {
    "specifiers": {
      "type": "object",
      "required": [
        "climate_forcing",
        "ensemble_member",
        "climate_scenario",
        "climate_variable",
        "resolution",
        "region",
        "time_step"
      ],
      "properties": {
        "ensemble_member": {
          "type": "string",
          "enum": [
            "r1i1p1f2",
            "r4i1p1f1",
            "r1i1p1f1"
          ]
        },
        "climate_scenario": {
          "type": "string",
          "enum": [
            "ssp585",
            "ssp370",
            "picontrol",
            "historical",
            "ssp126"
          ]
        },
        "climate_variable": {
          "type": "string",
          "enum": [
            "prsn",
            "tob",
            "zmicro",
            "phydiaz",
            "vo",
            "tas",
            "hurs",
            "expc",
            "intpppico",
            "ch4",
            "phypico",
            "thetao",
            "ph",
            "zooc",
            "o2",
            "rlds",
            "lightning",
            "phydiat",
            "rsntds",
            "pr",
            "uo",
            "intppdiaz",
            "so",
            "ps",
            "huss",
            "tos",
            "co2",
            "zmeso",
            "intppdiat",
            "siconc",
            "rsds",
            "wo",
            "tasmax",
            "sfcwind",
            "phyc",
            "mlotstmax",
            "intpoc",
            "thkcello",
            "chl",
            "intpp",
            "tasmin"
          ]
        },
        "resolution": {
          "type": "string",
          "enum": [
            "30arcsec",
            "60arcmin",
            "300arcsec",
            "30arcmin",
            "120arcmin",
            "1800arcsec",
            "15arcmin",
            "90arcsec"
          ]
        },
        "region": {
          "type": "string",
          "enum": [
            "global"
          ]
        },
        "time_step": {
          "type": "string",
          "enum": [
            "annual",
            "daily",
            "monthly",
            "fixed"
          ]
        }
      }
    }
  }
}