{
  "$schema": "http://json-schema.org/draft-07/schema#",
  "$id": "https://protocol.isimip.org/schema/schema/ISIMIP3b/OutputData/lakes_local.json",
  "commit": "ff32b43825ca571768eb691eaefc4e1b6e3b79de",
  "type": "object",
  "required": [
    "specifiers"
  ],
  "properties": {
    "specifiers": {
      "required": [
        "model",
        "climate_forcing",
        "bias_adjustment",
        "climate_scenario",
        "soc_scenario",
        "sens_scenario",
        "variable",
        "lake_site",
        "time_step"
      ],
      "properties": {
        "model": {
          "type": "string"
        },
        "climate_forcing": {
          "type": "string",
          "enum": [
            "mri-esm2-0",
            "ipsl-cm6a-lr",
            "mpi-esm1-2-hr",
            "ukesm1-0-ll",
            "gfdl-esm4"
          ]
        },
        "bias_adjustment": {
          "type": "string",
          "enum": [
            "w5e5",
            "nobasd"
          ]
        },
        "climate_scenario": {
          "type": "string",
          "enum": [
            "ssp370",
            "picontrol",
            "ssp126",
            "historical",
            "ssp585"
          ]
        },
        "soc_scenario": {
          "type": "string",
          "enum": [
            "1850soc",
            "histsoc",
            "2015soc",
            "nat"
          ]
        },
        "sens_scenario": {
          "type": "string",
          "enum": [
            "default"
          ]
        },
        "variable": {
          "type": "string",
          "enum": [
            "ice",
            "extcoeff",
            "tdn",
            "doc",
            "do",
            "lakeicefrac",
            "sedheatf",
            "snowtemp",
            "lakealbedo",
            "tp",
            "strat",
            "snowthick",
            "phytobio",
            "sensheatf",
            "icethick",
            "icetemp",
            "latentheatf",
            "chl",
            "tpd",
            "swup",
            "si",
            "lwup",
            "pn",
            "bottemp",
            "zoobio",
            "turbdiffheat",
            "surftemp",
            "momf",
            "pp",
            "lakeheatf",
            "thermodepth",
            "watertemp",
            "tn"
          ]
        },
        "lake_site": {
          "type": "string",
          "enum": [
            "washington",
            "tahoe",
            "erken",
            "kinneret",
            "taupo",
            "sparkling",
            "kivu",
            "sammamish",
            "big-muskellunge",
            "langtjern",
            "feeagh",
            "neuchatel",
            "waahi",
            "wingra",
            "tarawera",
            "kuivajarvi",
            "ngoring ",
            "burley-griffin",
            "rotorua",
            "vendyurskoe",
            "falling-creek",
            "klicava",
            "mt-bold",
            "mendota",
            "fish",
            "rimov",
            "windermere",
            "okauchee",
            "zlutice",
            "toolik",
            "annie",
            "alqueva",
            "geneva",
            "trout-lake",
            "harp",
            "esthwaite-water",
            "green",
            "nohipalo-mustjaerv",
            "rappbode",
            "ekoln ",
            "great",
            "black-oak",
            "two-sisters",
            "mueggelsee",
            "sau",
            "laramie",
            "biel",
            "vortsjaerv",
            "monona",
            "argyle",
            "crystal-lake",
            "paajarvi",
            "nohipalo-valgejaerv",
            "dickie",
            "lower-zurich",
            "annecy",
            "sunapee",
            "stechlin",
            "delavan",
            "bourget",
            "mozhaysk",
            "crystal-bog",
            "kilpisjarvi",
            "trout-bog",
            "eagle "
          ]
        },
        "time_step": {
          "type": "string",
          "enum": [
            "daily",
            "monthly",
            "3hr",
            "fixed",
            "annual"
          ]
        },
        "start_year": {
          "type": "number"
        },
        "end_year": {
          "type": "number"
        }
      }
    }
  }
}