{
  "$schema": "http://json-schema.org/draft-07/schema#",
  "$id": "https://protocol.isimip.org/schema/schema/ISIMIP3b/OutputData/marine-fishery_regional.yaml",
  "commit": "2da166ba5623a60027585734b235d2319b761c06",
  "type": "object",
  "required": [
    "specifiers"
  ],
  "properties": {
    "specifiers": {
      "required": [
        "model",
        "climate_forcing",
        "bias_adjustment",
        "climate_scenario",
        "soc_scenario",
        "sens_scenario",
        "variable",
        "ocean_region",
        "time_step"
      ],
      "properties": {
        "model": {
          "type": "string"
        },
        "climate_forcing": {
          "type": "string",
          "enum": [
            "mpi-esm1-2-hr",
            "gfdl-esm4",
            "ukesm1-0-ll",
            "ipsl-cm6a-lr"
          ]
        },
        "bias_adjustment": {
          "type": "string",
          "enum": [
            "nobasd",
            "w5e5"
          ]
        },
        "climate_scenario": {
          "type": "string",
          "enum": [
            "ssp126",
            "picontrol",
            "ssp585",
            "historical",
            "ssp370"
          ]
        },
        "soc_scenario": {
          "type": "string",
          "enum": [
            "histsoc",
            "nat",
            "2015soc-from-histsoc"
          ]
        },
        "sens_scenario": {
          "type": "string",
          "enum": [
            "default",
            "2015co2"
          ]
        },
        "variable": {
          "type": "string",
          "enum": [
            "tcblog10",
            "cd90cm",
            "cp30to90cm",
            "cp30cm",
            "cd30cm",
            "tc",
            "tclog10",
            "bd30cm",
            "tcb",
            "bp90cm",
            "bp30cm",
            "bd90cm",
            "tpc",
            "tpb",
            "tdb",
            "bp30to90cm",
            "tdc",
            "cp90cm",
            "bd30to90cm",
            "cd30to90cm"
          ]
        },
        "ocean_region": {
          "type": "string",
          "enum": [
            "humboldt-n",
            "northsea-ibts",
            "northernhumboldt",
            "north-sea",
            "eastern-scotian-shelf",
            "seaustralia-mizer",
            "se-australia",
            "gulf-alaska",
            "hawaiian-longline",
            "seaustralia-atlantis",
            "hawaii",
            "nw-med-sea",
            "baltic-sea",
            "med-glob",
            "taiwancentralsouthpacific",
            "northsea-ewe",
            "benguela",
            "east-bering-sea",
            "chatham-rise-ll-nz",
            "prydz-bay",
            "adriatic-sea",
            "mediterraneansea",
            "east-bearing-sea-shelf",
            "cook-strait",
            "east-bass-strait",
            "tasman-golden-bays-nz",
            "kerguelen",
            "himi",
            "brasil-ne"
          ]
        },
        "time_step": {
          "type": "string",
          "enum": [
            "annual",
            "3hr",
            "fixed",
            "monthly",
            "hourly",
            "daily"
          ]
        },
        "start_year": {
          "type": "number"
        },
        "end_year": {
          "type": "number"
        }
      }
    }
  }
}